secretaries/__init__.py
secretaries/patterns.py
secretaries/secretary.py
secretaries/starter_kit_safe_words_en.csv
secretaries/startkit_ickenamn_se.csv
secretaries/utils.py
secretaries-0.0.1.13.dist-info/METADATA
secretaries-0.0.1.13.dist-info/WHEEL
secretaries-0.0.1.13.dist-info/licenses/LICENSE
secretaries-0.0.1.13.dist-info/RECORD
