Metadata-Version: 2.4
Name: secretaries
Version: 0.0.1.13
Summary: A utility for removing personal data in text.
Project-URL: Homepage, https://github.com/er1kb/secretaries
Project-URL: Bug Tracker, https://github.com/er1kb/secretaries/issues
Author-email: Erik Broman <mikroberna@gmail.com>
License-Expression: MIT
License-File: LICENSE
Keywords: anonymization,gdpr,personal data,personuppgifter,python
Classifier: Development Status :: 3 - Alpha
Classifier: Intended Audience :: Other Audience
Classifier: License :: OSI Approved :: MIT License
Classifier: Natural Language :: English
Classifier: Natural Language :: Swedish
Classifier: Operating System :: OS Independent
Classifier: Programming Language :: Python :: 3 :: Only
Requires-Python: >=3.9
Requires-Dist: importlib-resources>=6.1.0
Requires-Dist: nltk>=3.8.1
Requires-Dist: polars>=0.19.2
Requires-Dist: torch>=1.13.1
Requires-Dist: transformers>=4.33.1
